[
    {
        "title": "Lorem ipsum dolor sit.",
        "image": "https://vis-society.github.io/labs/2/images/empty.svg",
        "description": "Lorem ipsum dolor sit."
    },
    {
        "title": "Odio qui nostrum accusantium.",
        "image": "https://vis-society.github.io/labs/2/images/empty.svg",
        "description": "Nulla mollitia quibusdam ratione."
    },
    {
        "title": "Quia a repellendus cum!",
        "image": "https://vis-society.github.io/labs/2/images/empty.svg",
        "description": "Obcaecati quasi voluptates esse!"
    },
    {
        "title": "Itaque eveniet ab accusantium.",
        "image": "https://vis-society.github.io/labs/2/images/empty.svg",
        "description": "Suscipit autem eum consequuntur?"
    },
    {
        "title": "Natus dolorum hic fugiat!",
        "image": "https://vis-society.github.io/labs/2/images/empty.svg",
        "description": "Nulla voluptatem beatae doloribus?"
    },
    {
        "title": "Sunt animi nihil obcaecati.",
        "image": "https://vis-society.github.io/labs/2/images/empty.svg",
        "description": "Quo fugit itaque sint!"
    },
    {
        "title": "Ab iste reprehenderit aspernatur!",
        "image": "https://vis-society.github.io/labs/2/images/empty.svg",
        "description": "Architecto voluptatum impedit iste!"
    },
    {
        "title": "Autem mollitia repudiandae nobis.",
        "image": "https://vis-society.github.io/labs/2/images/empty.svg",
        "description": "Quasi inventore illum numquam?"
    },
    {
        "title": "Ipsam facilis enim quos.",
        "image": "https://vis-society.github.io/labs/2/images/empty.svg",
        "description": "Excepturi enim illum cum."
    },
    {
        "title": "Excepturi perferendis laborum minima!",
        "image": "https://vis-society.github.io/labs/2/images/empty.svg",
        "description": "Quae praesentium omnis a."
    },
    {
        "title": "Recusandae asperiores quo suscipit.",
        "image": "https://vis-society.github.io/labs/2/images/empty.svg",
        "description": "Aspernatur, itaque quod! Excepturi!"
    },
    {
        "title": "Laborum recusandae repellat sunt.",
        "image": "https://vis-society.github.io/labs/2/images/empty.svg",
        "description": "Repellat nihil dicta ducimus!"
    }
]